depmap_downloader/version.py
depmap_downloader/__init__.py
depmap_downloader/api.py
depmap_downloader/cli.py
depmap_downloader/py.typed
depmap_downloader/__main__.py
depmap_downloader-0.0.3.dist-info/licenses/LICENSE
depmap_downloader-0.0.3.dist-info/WHEEL
depmap_downloader-0.0.3.dist-info/entry_points.txt
depmap_downloader-0.0.3.dist-info/METADATA
depmap_downloader-0.0.3.dist-info/RECORD
