Metadata-Version: 2.4
Name: depmap-downloader
Version: 0.0.3
Summary: Reproducibly download the latest version of DepMap datasets
Keywords: snekpack,cookiecutter,depmap,cancer dependency map,bioinformatics,cancer
Author: Charles Tapley Hoyt
Author-email: Charles Tapley Hoyt <cthoyt@gmail.com>
License-File: LICENSE
Classifier: Development Status :: 1 - Planning
Classifier: Environment :: Console
Classifier: Intended Audience :: Developers
Classifier: License :: OSI Approved :: MIT License
Classifier: Operating System :: OS Independent
Classifier: Framework :: Pytest
Classifier: Framework :: tox
Classifier: Framework :: Sphinx
Classifier: Natural Language :: English
Classifier: Programming Language :: Python
Classifier: Programming Language :: Python :: 3.10
Classifier: Programming Language :: Python :: 3.11
Classifier: Programming Language :: Python :: 3.12
Classifier: Programming Language :: Python :: 3.13
Classifier: Programming Language :: Python :: 3 :: Only
Classifier: Typing :: Typed
Requires-Dist: click
Requires-Dist: more-click
Requires-Dist: typing-extensions
Requires-Dist: requests
Requires-Dist: pystow
Requires-Dist: beautifulsoup4
Maintainer: Charles Tapley Hoyt
Maintainer-email: Charles Tapley Hoyt <cthoyt@gmail.com>
Requires-Python: >=3.10
Project-URL: Bug Tracker, https://github.com/cthoyt/depmap-downloader/issues
Project-URL: Documentation, https://depmap_downloader.readthedocs.io
Project-URL: Funding, https://github.com/sponsors/cthoyt
Project-URL: Homepage, https://github.com/cthoyt/depmap-downloader
Project-URL: Repository, https://github.com/cthoyt/depmap-downloader.git
